sbox/__init__.py
sbox-1.1.0.dist-info/METADATA
sbox-1.1.0.dist-info/WHEEL
sbox-1.1.0.dist-info/top_level.txt
sbox-1.1.0.dist-info/RECORD
