Metadata-Version: 2.4
Name: sbox
Version: 1.1.0
Summary: A simple secret manager with Pydantic model migration support
Author-email: evryoneowo <evryhvh@gmail.com>
License: MIT
Project-URL: Homepage, https://github.com/evryoneowo/sbox
Classifier: Programming Language :: Python :: 3
Classifier: License :: OSI Approved :: MIT License
Requires-Dist: pydantic>=2.0.0
